dokken-0.1.1.dist-info/licenses/LICENSE
src/__init__.py
src/cache.py
src/constants.py
src/exceptions.py
src/file_utils.py
src/main.py
src/records.py
src/workflows.py
src/config/__init__.py
src/config/loader.py
src/config/merger.py
src/config/models.py
src/config/types.py
src/doctypes/__init__.py
src/doctypes/configs.py
src/doctypes/types.py
src/input/__init__.py
src/input/code_analyzer.py
src/input/human_in_the_loop.py
src/llm/__init__.py
src/llm/llm.py
src/llm/prompt_builder.py
src/llm/prompts.py
src/output/__init__.py
src/output/formatters.py
src/output/merger.py
src/security/__init__.py
src/security/input_validation.py
dokken-0.1.1.dist-info/METADATA
dokken-0.1.1.dist-info/WHEEL
dokken-0.1.1.dist-info/entry_points.txt
dokken-0.1.1.dist-info/top_level.txt
dokken-0.1.1.dist-info/RECORD
