Metadata-Version: 2.4
Name: dokken
Version: 0.1.1
Summary: AI-powered documentation generation and drift detection tool
Requires-Python: >=3.10
License-File: LICENSE
Requires-Dist: click>=8.3.1
Requires-Dist: llama-index>=0.14.12
Requires-Dist: llama-index-llms-anthropic>=0.10.5
Requires-Dist: llama-index-llms-google-genai>=0.8.3
Requires-Dist: llama-index-llms-openai>=0.6.13
Requires-Dist: pydantic>=2.12.5
Requires-Dist: python-dotenv>=1.2.1
Requires-Dist: questionary>=2.1.1
Requires-Dist: rich>=14.2.0
Requires-Dist: tomli>=2.4.0; python_version < "3.11"
Dynamic: license-file
